{
  "tag": "initial-access",
  "locale": "en",
  "intro": "This archive collects 8 articles tagged `initial-access` published between April 14, 2026 and April 25, 2026. Coverage includes 8 high reports. Individual reports below detail the specific incidents, affected systems, and recommended mitigations for security teams tracking this topic.",
  "sources_hash": "f4e6102e7daafccd",
  "model": "template:sparse",
  "generated_at": "2026-04-26T04:13:51.382Z",
  "prompt_version": "v1.1.0-2026-04-20"
}
